<?xml version="1.0"?>
<!DOCTYPE hibernate-mapping PUBLIC "-//Hibernate/Hibernate Mapping DTD 3.0//EN"
"http://hibernate.sourceforge.net/hibernate-mapping-3.0.dtd">
<!-- Generated 2015-11-15 12:00:11 by Hibernate Tools 3.4.0.CR1 -->
<hibernate-mapping>
    <class name="modele.hibernate.Tblgenre" table="TBLGENRE" schema="TRD157_23">
        <id name="nomgenre" type="string">
            <column name="NOMGENRE" length="25" />
            <generator class="assigned" />
        </id>
        <set name="tblfilms" table="TBLFILMGENRE" inverse="true" lazy="true" fetch="select">
            <key>
                <column name="NOMGENRE" length="25" not-null="true" />
            </key>
            <many-to-many entity-name="modele.hibernate.Tblfilm">
                <column name="IDFILM" precision="22" scale="0" not-null="true" />
            </many-to-many>
        </set>
    </class>
</hibernate-mapping>
